<?xml version="1.0" encoding="UTF-8"?>

<features name="karaf-weather-cxf-${project.version}" xmlns="http://karaf.apache.org/xmlns/features/v1.4.0" xmlns:xsi="http://www.w3.org/2001/XMLSchema-instance" xsi:schemaLocation="http://karaf.apache.org/xmlns/features/v1.4.0">

    <repository>mvn:org.apache.cxf.karaf/apache-cxf/3.1.5/xml/features</repository>

    <feature name="weather-service-impl" version="${project.version}">
        <bundle>mvn:org.example/weather-service-impl/${project.version}</bundle>
    </feature>

    <feature name="karaf-rest-weather-blueprint" version="${project.version}">
        <feature version="${project.version}">weather-service-impl</feature>
        <bundle>mvn:com.fasterxml.jackson.core/jackson-core/${jackson.version}</bundle>
        <bundle>mvn:com.fasterxml.jackson.core/jackson-annotations/${jackson.version}</bundle>
        <bundle>mvn:com.fasterxml.jackson.core/jackson-databind/${jackson.version}</bundle>
        <bundle>mvn:com.fasterxml.jackson.jaxrs/jackson-jaxrs-base/${jackson.version}</bundle>
        <bundle>mvn:com.fasterxml.jackson.jaxrs/jackson-jaxrs-json-provider/${jackson.version}</bundle>
        <bundle>mvn:org.example/karaf-rest-weather-blueprint/${project.version}</bundle>
    </feature>


</features>